{
  "used": [
    0,
    1,
    2,
    3,
    4,
    5,
    6,
    7,
    8
  ],
  "posted": [
    {
      "when": "2026-07-19T07:48:04Z",
      "idx": 0,
      "quote": "Du bist nicht zu viel.|*Du warst nur zu lange leise.",
      "media_id": "18014343674911498",
      "permalink": "https://www.instagram.com/stories/kopfundkompass/3944552103960058627"
    },
    {
      "when": "2026-07-19T16:25:13Z",
      "idx": 1,
      "quote": "Ruhe ist keine Schwäche.|*Sie ist Kontrolle.",
      "media_id": "18000095879977865",
      "permalink": "https://www.instagram.com/stories/kopfundkompass/3944812416399812429"
    },
    {
      "when": "2026-07-20T08:21:25Z",
      "idx": 2,
      "quote": "Disziplin ist Selbstachtung,|*in Handlung übersetzt.",
      "media_id": "17939983644084973",
      "permalink": "https://www.instagram.com/stories/kopfundkompass/3945293661520837300"
    },
    {
      "when": "2026-07-20T16:52:23Z",
      "idx": 3,
      "quote": "Nicht jeder verdient|*eine Antwort von dir.",
      "media_id": "17976066669075323",
      "permalink": "https://www.instagram.com/stories/kopfundkompass/3945550871896554203"
    },
    {
      "when": "2026-07-21T07:45:12Z",
      "idx": 4,
      "quote": "Loslassen heisst nicht aufgeben.|*Es heisst Platz machen.",
      "media_id": "18108969778994049",
      "permalink": "https://www.instagram.com/stories/kopfundkompass/3946000184312114113"
    },
    {
      "when": "2026-07-21T16:52:28Z",
      "idx": 5,
      "quote": "Klarheit kommt nicht vor dem Mut.|*Sie kommt danach.",
      "media_id": "17944450122252808",
      "permalink": "https://www.instagram.com/stories/kopfundkompass/3946275662936518337"
    },
    {
      "when": "2026-07-22T07:45:21Z",
      "idx": 6,
      "quote": "Grenzen sind kein Streit.|*Sie sind Selbstschutz.",
      "media_id": "17876286582522829",
      "permalink": "https://www.instagram.com/stories/kopfundkompass/3946725030080703526"
    },
    {
      "when": "2026-07-22T16:54:30Z",
      "idx": 7,
      "quote": "Geduld ist nicht Warten.|*Es ist Vertrauen mit Ausdauer.",
      "media_id": "18439227328193561",
      "permalink": "https://www.instagram.com/stories/kopfundkompass/3947001407207550252"
    },
    {
      "when": "2026-07-23T07:54:30Z",
      "idx": 8,
      "quote": "Dein Wert sinkt nicht,|*weil jemand ihn nicht sieht.",
      "media_id": "18066421790502032",
      "permalink": "https://www.instagram.com/stories/kopfundkompass/3947454426860891688"
    }
  ]
}